LICENSE
MANIFEST.in
README.rst
setup.cfg
setup.py
vaccontrib/__init__.py
vaccontrib/covid.py
vaccontrib/illustration.py
vaccontrib/io.py
vaccontrib/linalg.py
vaccontrib/main.py
vaccontrib/metadata.py
vaccontrib/mock_samplable_set.py
vaccontrib/paths.py
vaccontrib/plot.py
vaccontrib/sim.py
vaccontrib.egg-info/PKG-INFO
vaccontrib.egg-info/SOURCES.txt
vaccontrib.egg-info/dependency_links.txt
vaccontrib.egg-info/not-zip-safe
vaccontrib.egg-info/requires.txt
vaccontrib.egg-info/top_level.txt
vaccontrib/data/contact_matrix.csv
vaccontrib/data/population.csv
vaccontrib/data/relative_infection_rate_alpha.csv
vaccontrib/data/relative_infection_rate_delta.csv
vaccontrib/data/relative_recovery_rate_alpha.csv
vaccontrib/data/relative_recovery_rate_delta.csv
vaccontrib/data/susceptibility_reduction_alpha.csv
vaccontrib/data/susceptibility_reduction_delta.csv
vaccontrib/data/transmissibility_reduction_alpha.csv
vaccontrib/data/transmissibility_reduction_delta.csv
vaccontrib/data/vaccinated.csv
vaccontrib/data/vaccine_fractions.csv
vaccontrib/tests/__init__.py
vaccontrib/tests/matrix_tests.py