Metadata-Version: 1.2
Name: vaccontrib
Version: 0.0.1
Summary: Quantifying the contributions vaccinated individuals make towards the effective reproduction number.
Home-page: https://github.com/benmaier/vaccontrib
Author: Benjamin F. Maier
Author-email: contact@benmaier.org
License: MIT
Project-URL: Documentation, http://vaccontrib.readthedocs.io
Project-URL: Contributing Statement, https://github.com/benmaier/vaccontrib/blob/master/CONTRIBUTING.md
Project-URL: Bug Reports, https://github.com/benmaier/vaccontrib/issues
Project-URL: Source, https://github.com/benmaier/vaccontrib/
Project-URL: PyPI, https://pypi.org/project/vaccontrib/
Platform: UNKNOWN
Classifier: License :: OSI Approved :: MIT License
Classifier: Programming Language :: Python :: 3.6
Classifier: Programming Language :: Python :: 3.7
Classifier: Programming Language :: Python :: 3.8
Requires-Python: >=3.6
